filedbm/__init__.py
filedbm/main.py
filedbm/utils.py
filedbm/tests/__init__.py
filedbm-0.0.6.dist-info/LICENSE
filedbm-0.0.6.dist-info/METADATA
filedbm-0.0.6.dist-info/WHEEL
filedbm-0.0.6.dist-info/top_level.txt
filedbm-0.0.6.dist-info/RECORD
