Metadata-Version: 2.1
Name: filedbm
Version: 0.0.6
Summary: A persistent key-value database
Home-page: https://github.com/mullenkamp/filedbm
Author: Mike Kittridge
Author-email: mullenkamp1@gmail.com
License: Apache
Keywords: shelve dbm
Classifier: Development Status :: 3 - Alpha
Classifier: Intended Audience :: Developers
Classifier: License :: OSI Approved :: Apache Software License
Classifier: Programming Language :: Python :: 3.8
Classifier: Programming Language :: Python :: 3.9
License-File: LICENSE
